ceca_sorter/__init__.py
ceca_sorter/__main__.py
ceca_sorter/ceca_sorter_base.py
ceca_sorter-1.0.dist-info/LICENSE
ceca_sorter-1.0.dist-info/METADATA
ceca_sorter-1.0.dist-info/WHEEL
ceca_sorter-1.0.dist-info/entry_points.txt
ceca_sorter-1.0.dist-info/top_level.txt
ceca_sorter-1.0.dist-info/RECORD
