Metadata-Version: 2.1
Name: ceca-sorter
Version: 1.0
Summary: Python imports sorter written for Comparaencasa utilities
Author: Martin Nieva
Author-email: martinjafactor@gmail.com
License: UNKNOWN
Platform: UNKNOWN
License-File: LICENSE
Requires-Dist: click
